radlibs/__init__.py
radlibs/generatewordopts.py
radlibs/makeradlibs.py
radlibs/postagger.py
radlibs/data/humor_dataset.feather
radlibs/data/pos_lexicon.feather
radlibs/data/proper_nouns.feather
radlibs-0.2.0.dist-info/METADATA
radlibs-0.2.0.dist-info/WHEEL
radlibs-0.2.0.dist-info/top_level.txt
radlibs-0.2.0.dist-info/RECORD
